Suarimhellopack/__init__.py
Suarimhellopack/hello.py
SuarimHelloPack-0.1.0.dist-info/METADATA
SuarimHelloPack-0.1.0.dist-info/WHEEL
SuarimHelloPack-0.1.0.dist-info/top_level.txt
SuarimHelloPack-0.1.0.dist-info/RECORD
