Metadata-Version: 2.1
Name: SuarimHelloPack
Version: 0.1.0
Summary: A simple HelloWorld package by Suarim
Home-page: https://github.com/yourusername/SuarimHelloPack
Author: Suarim
Author-email: your.email@example.com
Classifier: Programming Language :: Python :: 3
Classifier: License :: OSI Approved :: MIT License
Classifier: Operating System :: OS Independent
Requires-Python: >=3.6
